django_logutils/middleware.py
django_logutils/__init__.py
django_logutils/utils.py
django_logutils/conf.py
django_logutils/models.py
django_logutils/static/css/django_logutils.css
django_logutils/static/js/django_logutils.js
django_logutils/templates/django_logutils/base.html
django_logutils-0.4.3.dist-info/WHEEL
django_logutils-0.4.3.dist-info/METADATA
django_logutils-0.4.3.dist-info/metadata.json
django_logutils-0.4.3.dist-info/DESCRIPTION.rst
django_logutils-0.4.3.dist-info/top_level.txt
django_logutils-0.4.3.dist-info/RECORD
