Metadata-Version: 2.0
Name: django-logutils
Version: 0.4.3
Summary: Various logging-related utilities for Django projects.
Home-page: https://github.com/jsmits/django-logutils
Author: Sander Smits
Author-email: jhmsmits@gmail.com
License: BSD
Keywords: django-logutils
Platform: UNKNOWN
Classifier: Development Status :: 4 - Beta
Classifier: Framework :: Django
Classifier: Intended Audience :: Developers
Classifier: License :: OSI Approved :: BSD License
Classifier: Natural Language :: English
Classifier: Programming Language :: Python :: 2
Classifier: Programming Language :: Python :: 2.7
Classifier: Programming Language :: Python :: 3
Classifier: Programming Language :: Python :: 3.4
Classifier: Programming Language :: Python :: 3.5
Classifier: Programming Language :: Python :: 3.6
Requires-Dist: django
Requires-Dist: django-appconf
